<?xml version="1.0" encoding="UTF-8"?>
<?xml-stylesheet type="text/xsl" href="receipt.xsl"?>
<RECEIPT receiptDate="2017-02-06T19:53:45.298Z" submissionFile="sample.PACA-CA.wgs_1471875212.submission-1471875212_752a6531-784b-4142-8b54-bace3378a41a.xml" success="true">
  <SAMPLE accession="EGAN00001376584" alias="SA533666" status="PRIVATE">
    <EXT_ID accession="SAMEA3902018" type="biosample"/>
  </SAMPLE>
  <SAMPLE accession="EGAN00001376586" alias="SA533768" status="PRIVATE">
    <EXT_ID accession="SAMEA3902020" type="biosample"/>
  </SAMPLE>
  <SAMPLE accession="EGAN00001376588" alias="SA533684" status="PRIVATE">
    <EXT_ID accession="SAMEA3902022" type="biosample"/>
  </SAMPLE>
  <SAMPLE accession="EGAN00001376590" alias="SA533721" status="PRIVATE">
    <EXT_ID accession="SAMEA3902024" type="biosample"/>
  </SAMPLE>
  <SAMPLE accession="EGAN00001376592" alias="SA520312" status="PRIVATE">
    <EXT_ID accession="SAMEA3902026" type="biosample"/>
  </SAMPLE>
  <SAMPLE accession="EGAN00001376594" alias="SA520221" status="PRIVATE">
    <EXT_ID accession="SAMEA3902028" type="biosample"/>
  </SAMPLE>
  <SAMPLE accession="EGAN00001376595" alias="SA544335" status="PRIVATE">
    <EXT_ID accession="SAMEA3902029" type="biosample"/>
  </SAMPLE>
  <SAMPLE accession="EGAN00001376596" alias="SA542454" status="PRIVATE">
    <EXT_ID accession="SAMEA3902030" type="biosample"/>
  </SAMPLE>
  <SAMPLE accession="EGAN00001376598" alias="SA533726" status="PRIVATE">
    <EXT_ID accession="SAMEA3902032" type="biosample"/>
  </SAMPLE>
  <SAMPLE accession="EGAN00001376600" alias="SA533780" status="PRIVATE">
    <EXT_ID accession="SAMEA3902034" type="biosample"/>
  </SAMPLE>
  <SAMPLE accession="EGAN00001376602" alias="SA533784" status="PRIVATE">
    <EXT_ID accession="SAMEA3902036" type="biosample"/>
  </SAMPLE>
  <SAMPLE accession="EGAN00001376604" alias="SA533773" status="PRIVATE">
    <EXT_ID accession="SAMEA3902038" type="biosample"/>
  </SAMPLE>
  <SAMPLE accession="EGAN00001376606" alias="SA533750" status="PRIVATE">
    <EXT_ID accession="SAMEA3902040" type="biosample"/>
  </SAMPLE>
  <SAMPLE accession="EGAN00001376608" alias="SA520290" status="PRIVATE">
    <EXT_ID accession="SAMEA3902042" type="biosample"/>
  </SAMPLE>
  <SAMPLE accession="EGAN00001376610" alias="SA520252" status="PRIVATE">
    <EXT_ID accession="SAMEA3902044" type="biosample"/>
  </SAMPLE>
  <SAMPLE accession="EGAN00001376612" alias="SA533674" status="PRIVATE">
    <EXT_ID accession="SAMEA3902046" type="biosample"/>
  </SAMPLE>
  <SAMPLE accession="EGAN00001376614" alias="SA520187" status="PRIVATE">
    <EXT_ID accession="SAMEA3902048" type="biosample"/>
  </SAMPLE>
  <SAMPLE accession="EGAN00001376616" alias="SA533665" status="PRIVATE">
    <EXT_ID accession="SAMEA3902050" type="biosample"/>
  </SAMPLE>
  <SAMPLE accession="EGAN00001376618" alias="SA533734" status="PRIVATE">
    <EXT_ID accession="SAMEA3902052" type="biosample"/>
  </SAMPLE>
  <SAMPLE accession="EGAN00001376620" alias="SA520168" status="PRIVATE">
    <EXT_ID accession="SAMEA3902054" type="biosample"/>
  </SAMPLE>
  <SAMPLE accession="EGAN00001376622" alias="SA533663" status="PRIVATE">
    <EXT_ID accession="SAMEA3902056" type="biosample"/>
  </SAMPLE>
  <SAMPLE accession="EGAN00001376624" alias="SA533643" status="PRIVATE">
    <EXT_ID accession="SAMEA3902058" type="biosample"/>
  </SAMPLE>
  <SAMPLE accession="EGAN00001376626" alias="SA533653" status="PRIVATE">
    <EXT_ID accession="SAMEA3902060" type="biosample"/>
  </SAMPLE>
  <SAMPLE accession="EGAN00001376628" alias="SA520223" status="PRIVATE">
    <EXT_ID accession="SAMEA3902062" type="biosample"/>
  </SAMPLE>
  <SAMPLE accession="EGAN00001376632" alias="SA533585" status="PRIVATE">
    <EXT_ID accession="SAMEA3902066" type="biosample"/>
  </SAMPLE>
  <SAMPLE accession="EGAN00001376634" alias="SA533803" status="PRIVATE">
    <EXT_ID accession="SAMEA3902068" type="biosample"/>
  </SAMPLE>
  <SAMPLE accession="EGAN00001376636" alias="SA520264" status="PRIVATE">
    <EXT_ID accession="SAMEA3902070" type="biosample"/>
  </SAMPLE>
  <SAMPLE accession="EGAN00001376638" alias="SA533704" status="PRIVATE">
    <EXT_ID accession="SAMEA3902072" type="biosample"/>
  </SAMPLE>
  <SAMPLE accession="EGAN00001376640" alias="SA533613" status="PRIVATE">
    <EXT_ID accession="SAMEA3902074" type="biosample"/>
  </SAMPLE>
  <SAMPLE accession="EGAN00001376642" alias="SA558653" status="PRIVATE">
    <EXT_ID accession="SAMEA3902076" type="biosample"/>
  </SAMPLE>
  <SAMPLE accession="EGAN00001376644" alias="SA533749" status="PRIVATE">
    <EXT_ID accession="SAMEA3902078" type="biosample"/>
  </SAMPLE>
  <SAMPLE accession="EGAN00001376646" alias="SA520274" status="PRIVATE">
    <EXT_ID accession="SAMEA3902080" type="biosample"/>
  </SAMPLE>
  <SAMPLE accession="EGAN00001376648" alias="SA533797" status="PRIVATE">
    <EXT_ID accession="SAMEA3902082" type="biosample"/>
  </SAMPLE>
  <SAMPLE accession="EGAN00001376650" alias="SA533811" status="PRIVATE">
    <EXT_ID accession="SAMEA3902084" type="biosample"/>
  </SAMPLE>
  <SAMPLE accession="EGAN00001376652" alias="SA533676" status="PRIVATE">
    <EXT_ID accession="SAMEA3902086" type="biosample"/>
  </SAMPLE>
  <SAMPLE accession="EGAN00001376654" alias="SA558659" status="PRIVATE">
    <EXT_ID accession="SAMEA3902088" type="biosample"/>
  </SAMPLE>
  <SAMPLE accession="EGAN00001376656" alias="SA533686" status="PRIVATE">
    <EXT_ID accession="SAMEA3902090" type="biosample"/>
  </SAMPLE>
  <SAMPLE accession="EGAN00001376658" alias="SA520229" status="PRIVATE">
    <EXT_ID accession="SAMEA3902092" type="biosample"/>
  </SAMPLE>
  <SAMPLE accession="EGAN00001376660" alias="SA520239" status="PRIVATE">
    <EXT_ID accession="SAMEA3902094" type="biosample"/>
  </SAMPLE>
  <SAMPLE accession="EGAN00001376662" alias="SA520278" status="PRIVATE">
    <EXT_ID accession="SAMEA3902096" type="biosample"/>
  </SAMPLE>
  <SAMPLE accession="EGAN00001376664" alias="SA533801" status="PRIVATE">
    <EXT_ID accession="SAMEA3902098" type="biosample"/>
  </SAMPLE>
  <SAMPLE accession="EGAN00001376666" alias="SA520292" status="PRIVATE">
    <EXT_ID accession="SAMEA3902100" type="biosample"/>
  </SAMPLE>
  <SAMPLE accession="EGAN00001376668" alias="SA533764" status="PRIVATE">
    <EXT_ID accession="SAMEA3902102" type="biosample"/>
  </SAMPLE>
  <SAMPLE accession="EGAN00001376670" alias="SA533580" status="PRIVATE">
    <EXT_ID accession="SAMEA3902104" type="biosample"/>
  </SAMPLE>
  <SAMPLE accession="EGAN00001376672" alias="SA533747" status="PRIVATE">
    <EXT_ID accession="SAMEA3902106" type="biosample"/>
  </SAMPLE>
  <SAMPLE accession="EGAN00001376674" alias="SA520182" status="PRIVATE">
    <EXT_ID accession="SAMEA3902108" type="biosample"/>
  </SAMPLE>
  <SAMPLE accession="EGAN00001376676" alias="SA520169" status="PRIVATE">
    <EXT_ID accession="SAMEA3902110" type="biosample"/>
  </SAMPLE>
  <SAMPLE accession="EGAN00001376678" alias="SA533725" status="PRIVATE">
    <EXT_ID accession="SAMEA3902112" type="biosample"/>
  </SAMPLE>
  <SAMPLE accession="EGAN00001376680" alias="SA520270" status="PRIVATE">
    <EXT_ID accession="SAMEA3902114" type="biosample"/>
  </SAMPLE>
  <SAMPLE accession="EGAN00001376682" alias="SA520201" status="PRIVATE">
    <EXT_ID accession="SAMEA3902116" type="biosample"/>
  </SAMPLE>
  <SAMPLE accession="EGAN00001376686" alias="SA533741" status="PRIVATE">
    <EXT_ID accession="SAMEA3902120" type="biosample"/>
  </SAMPLE>
  <SAMPLE accession="EGAN00001376688" alias="SA520318" status="PRIVATE">
    <EXT_ID accession="SAMEA3902122" type="biosample"/>
  </SAMPLE>
  <SAMPLE accession="EGAN00001376689" alias="SA533799" status="PRIVATE">
    <EXT_ID accession="SAMEA3902123" type="biosample"/>
  </SAMPLE>
  <SAMPLE accession="EGAN00001376690" alias="SA533688" status="PRIVATE">
    <EXT_ID accession="SAMEA3902124" type="biosample"/>
  </SAMPLE>
  <SAMPLE accession="EGAN00001376692" alias="SA533709" status="PRIVATE">
    <EXT_ID accession="SAMEA3902126" type="biosample"/>
  </SAMPLE>
  <SAMPLE accession="EGAN00001376696" alias="SA533757" status="PRIVATE">
    <EXT_ID accession="SAMEA3902130" type="biosample"/>
  </SAMPLE>
  <SAMPLE accession="EGAN00001376698" alias="SA533786" status="PRIVATE">
    <EXT_ID accession="SAMEA3902132" type="biosample"/>
  </SAMPLE>
  <SAMPLE accession="EGAN00001376699" alias="SA533640" status="PRIVATE">
    <EXT_ID accession="SAMEA3902133" type="biosample"/>
  </SAMPLE>
  <SAMPLE accession="EGAN00001376700" alias="SA533615" status="PRIVATE">
    <EXT_ID accession="SAMEA3902134" type="biosample"/>
  </SAMPLE>
  <SAMPLE accession="EGAN00001376702" alias="SA533639" status="PRIVATE">
    <EXT_ID accession="SAMEA3902136" type="biosample"/>
  </SAMPLE>
  <SAMPLE accession="EGAN00001376704" alias="SA520235" status="PRIVATE">
    <EXT_ID accession="SAMEA3902138" type="biosample"/>
  </SAMPLE>
  <SAMPLE accession="EGAN00001376706" alias="SA533652" status="PRIVATE">
    <EXT_ID accession="SAMEA3902140" type="biosample"/>
  </SAMPLE>
  <SAMPLE accession="EGAN00001376708" alias="SA533690" status="PRIVATE">
    <EXT_ID accession="SAMEA3902142" type="biosample"/>
  </SAMPLE>
  <SAMPLE accession="EGAN00001376710" alias="SA533800" status="PRIVATE">
    <EXT_ID accession="SAMEA3902144" type="biosample"/>
  </SAMPLE>
  <SAMPLE accession="EGAN00001376712" alias="SA520300" status="PRIVATE">
    <EXT_ID accession="SAMEA3902146" type="biosample"/>
  </SAMPLE>
  <SAMPLE accession="EGAN00001376714" alias="SA533664" status="PRIVATE">
    <EXT_ID accession="SAMEA3902148" type="biosample"/>
  </SAMPLE>
  <SAMPLE accession="EGAN00001376716" alias="SA558699" status="PRIVATE">
    <EXT_ID accession="SAMEA3902150" type="biosample"/>
  </SAMPLE>
  <SAMPLE accession="EGAN00001376718" alias="SA558656" status="PRIVATE">
    <EXT_ID accession="SAMEA3902152" type="biosample"/>
  </SAMPLE>
  <SAMPLE accession="EGAN00001376720" alias="SA533713" status="PRIVATE">
    <EXT_ID accession="SAMEA3902154" type="biosample"/>
  </SAMPLE>
  <SAMPLE accession="EGAN00001376721" alias="SA533812" status="PRIVATE">
    <EXT_ID accession="SAMEA3902155" type="biosample"/>
  </SAMPLE>
  <SAMPLE accession="EGAN00001376722" alias="SA533695" status="PRIVATE">
    <EXT_ID accession="SAMEA3902156" type="biosample"/>
  </SAMPLE>
  <SAMPLE accession="EGAN00001376724" alias="SA533668" status="PRIVATE">
    <EXT_ID accession="SAMEA3902158" type="biosample"/>
  </SAMPLE>
  <SAMPLE accession="EGAN00001376726" alias="SA558655" status="PRIVATE">
    <EXT_ID accession="SAMEA3902160" type="biosample"/>
  </SAMPLE>
  <SAMPLE accession="EGAN00001376728" alias="SA520203" status="PRIVATE">
    <EXT_ID accession="SAMEA3902162" type="biosample"/>
  </SAMPLE>
  <SAMPLE accession="EGAN00001376730" alias="SA533746" status="PRIVATE">
    <EXT_ID accession="SAMEA3902164" type="biosample"/>
  </SAMPLE>
  <SAMPLE accession="EGAN00001376732" alias="SA520243" status="PRIVATE">
    <EXT_ID accession="SAMEA3902166" type="biosample"/>
  </SAMPLE>
  <SAMPLE accession="EGAN00001376734" alias="SA533779" status="PRIVATE">
    <EXT_ID accession="SAMEA3902168" type="biosample"/>
  </SAMPLE>
  <SAMPLE accession="EGAN00001376736" alias="SA520298" status="PRIVATE">
    <EXT_ID accession="SAMEA3902170" type="biosample"/>
  </SAMPLE>
  <SAMPLE accession="EGAN00001376738" alias="SA520181" status="PRIVATE">
    <EXT_ID accession="SAMEA3902172" type="biosample"/>
  </SAMPLE>
  <SAMPLE accession="EGAN00001376740" alias="SA520193" status="PRIVATE">
    <EXT_ID accession="SAMEA3902174" type="biosample"/>
  </SAMPLE>
  <SAMPLE accession="EGAN00001376742" alias="SA533681" status="PRIVATE">
    <EXT_ID accession="SAMEA3902176" type="biosample"/>
  </SAMPLE>
  <SAMPLE accession="EGAN00001376744" alias="SA533669" status="PRIVATE">
    <EXT_ID accession="SAMEA3902178" type="biosample"/>
  </SAMPLE>
  <SAMPLE accession="EGAN00001376746" alias="SA558678" status="PRIVATE">
    <EXT_ID accession="SAMEA3902180" type="biosample"/>
  </SAMPLE>
  <SAMPLE accession="EGAN00001376748" alias="SA533813" status="PRIVATE">
    <EXT_ID accession="SAMEA3902182" type="biosample"/>
  </SAMPLE>
  <SAMPLE accession="EGAN00001376750" alias="SA533796" status="PRIVATE">
    <EXT_ID accession="SAMEA3902184" type="biosample"/>
  </SAMPLE>
  <SAMPLE accession="EGAN00001376752" alias="SA533815" status="PRIVATE">
    <EXT_ID accession="SAMEA3902186" type="biosample"/>
  </SAMPLE>
  <SAMPLE accession="EGAN00001376754" alias="SA533736" status="PRIVATE">
    <EXT_ID accession="SAMEA3902188" type="biosample"/>
  </SAMPLE>
  <SAMPLE accession="EGAN00001376756" alias="SA520207" status="PRIVATE">
    <EXT_ID accession="SAMEA3902190" type="biosample"/>
  </SAMPLE>
  <SAMPLE accession="EGAN00001376757" alias="SA533752" status="PRIVATE">
    <EXT_ID accession="SAMEA3902191" type="biosample"/>
  </SAMPLE>
  <SAMPLE accession="EGAN00001376759" alias="SA533724" status="PRIVATE">
    <EXT_ID accession="SAMEA3902193" type="biosample"/>
  </SAMPLE>
  <SAMPLE accession="EGAN00001376761" alias="SA558658" status="PRIVATE">
    <EXT_ID accession="SAMEA3902195" type="biosample"/>
  </SAMPLE>
  <SAMPLE accession="EGAN00001376763" alias="SA533661" status="PRIVATE">
    <EXT_ID accession="SAMEA3902197" type="biosample"/>
  </SAMPLE>
  <SAMPLE accession="EGAN00001376765" alias="SA558710" status="PRIVATE">
    <EXT_ID accession="SAMEA3902199" type="biosample"/>
  </SAMPLE>
  <SAMPLE accession="EGAN00001376766" alias="SA533711" status="PRIVATE">
    <EXT_ID accession="SAMEA3902200" type="biosample"/>
  </SAMPLE>
  <SAMPLE accession="EGAN00001376767" alias="SA533744" status="PRIVATE">
    <EXT_ID accession="SAMEA3902201" type="biosample"/>
  </SAMPLE>
  <SAMPLE accession="EGAN00001376768" alias="SA533656" status="PRIVATE">
    <EXT_ID accession="SAMEA3902202" type="biosample"/>
  </SAMPLE>
  <SAMPLE accession="EGAN00001376769" alias="SA520262" status="PRIVATE">
    <EXT_ID accession="SAMEA3902203" type="biosample"/>
  </SAMPLE>
  <SAMPLE accession="EGAN00001376771" alias="SA533698" status="PRIVATE">
    <EXT_ID accession="SAMEA3902205" type="biosample"/>
  </SAMPLE>
  <SAMPLE accession="EGAN00001376777" alias="SA533682" status="PRIVATE">
    <EXT_ID accession="SAMEA3902211" type="biosample"/>
  </SAMPLE>
  <SAMPLE accession="EGAN00001376779" alias="SA533716" status="PRIVATE">
    <EXT_ID accession="SAMEA3902213" type="biosample"/>
  </SAMPLE>
  <SAMPLE accession="EGAN00001376781" alias="SA520304" status="PRIVATE">
    <EXT_ID accession="SAMEA3902215" type="biosample"/>
  </SAMPLE>
  <SAMPLE accession="EGAN00001376783" alias="SA533659" status="PRIVATE">
    <EXT_ID accession="SAMEA3902217" type="biosample"/>
  </SAMPLE>
  <SAMPLE accession="EGAN00001376785" alias="SA533772" status="PRIVATE">
    <EXT_ID accession="SAMEA3902219" type="biosample"/>
  </SAMPLE>
  <SAMPLE accession="EGAN00001376787" alias="SA533702" status="PRIVATE">
    <EXT_ID accession="SAMEA3902221" type="biosample"/>
  </SAMPLE>
  <SAMPLE accession="EGAN00001376789" alias="SA533770" status="PRIVATE">
    <EXT_ID accession="SAMEA3902223" type="biosample"/>
  </SAMPLE>
  <SAMPLE accession="EGAN00001376791" alias="SA520248" status="PRIVATE">
    <EXT_ID accession="SAMEA3902225" type="biosample"/>
  </SAMPLE>
  <SAMPLE accession="EGAN00001376793" alias="SA533718" status="PRIVATE">
    <EXT_ID accession="SAMEA3902227" type="biosample"/>
  </SAMPLE>
  <SAMPLE accession="EGAN00001376797" alias="SA533745" status="PRIVATE">
    <EXT_ID accession="SAMEA3902231" type="biosample"/>
  </SAMPLE>
  <SAMPLE accession="EGAN00001376801" alias="SA520282" status="PRIVATE">
    <EXT_ID accession="SAMEA3902235" type="biosample"/>
  </SAMPLE>
  <SAMPLE accession="EGAN00001376803" alias="SA558648" status="PRIVATE">
    <EXT_ID accession="SAMEA3902237" type="biosample"/>
  </SAMPLE>
  <SAMPLE accession="EGAN00001376805" alias="SA533660" status="PRIVATE">
    <EXT_ID accession="SAMEA3902239" type="biosample"/>
  </SAMPLE>
  <SAMPLE accession="EGAN00001376807" alias="SA533805" status="PRIVATE">
    <EXT_ID accession="SAMEA3902241" type="biosample"/>
  </SAMPLE>
  <SAMPLE accession="EGAN00001376809" alias="SA533619" status="PRIVATE">
    <EXT_ID accession="SAMEA3902243" type="biosample"/>
  </SAMPLE>
  <SAMPLE accession="EGAN00001376815" alias="SA533625" status="PRIVATE">
    <EXT_ID accession="SAMEA3902249" type="biosample"/>
  </SAMPLE>
  <SAMPLE accession="EGAN00001376817" alias="SA533743" status="PRIVATE">
    <EXT_ID accession="SAMEA3902251" type="biosample"/>
  </SAMPLE>
  <SAMPLE accession="EGAN00001376819" alias="SA533703" status="PRIVATE">
    <EXT_ID accession="SAMEA3902253" type="biosample"/>
  </SAMPLE>
  <SAMPLE accession="EGAN00001376821" alias="SA533729" status="PRIVATE">
    <EXT_ID accession="SAMEA3902255" type="biosample"/>
  </SAMPLE>
  <SAMPLE accession="EGAN00001376825" alias="SA533647" status="PRIVATE">
    <EXT_ID accession="SAMEA3902259" type="biosample"/>
  </SAMPLE>
  <SAMPLE accession="EGAN00001376827" alias="SA520215" status="PRIVATE">
    <EXT_ID accession="SAMEA3902261" type="biosample"/>
  </SAMPLE>
  <SAMPLE accession="EGAN00001376829" alias="SA558715" status="PRIVATE">
    <EXT_ID accession="SAMEA3902263" type="biosample"/>
  </SAMPLE>
  <SAMPLE accession="EGAN00001376831" alias="SA533730" status="PRIVATE">
    <EXT_ID accession="SAMEA3902265" type="biosample"/>
  </SAMPLE>
  <SAMPLE accession="EGAN00001376835" alias="SA533753" status="PRIVATE">
    <EXT_ID accession="SAMEA3902269" type="biosample"/>
  </SAMPLE>
  <SAMPLE accession="EGAN00001376837" alias="SA533758" status="PRIVATE">
    <EXT_ID accession="SAMEA3902271" type="biosample"/>
  </SAMPLE>
  <SAMPLE accession="EGAN00001376839" alias="SA533723" status="PRIVATE">
    <EXT_ID accession="SAMEA3902273" type="biosample"/>
  </SAMPLE>
  <SAMPLE accession="EGAN00001376841" alias="SA520283" status="PRIVATE">
    <EXT_ID accession="SAMEA3902275" type="biosample"/>
  </SAMPLE>
  <SAMPLE accession="EGAN00001376843" alias="SA533733" status="PRIVATE">
    <EXT_ID accession="SAMEA3902277" type="biosample"/>
  </SAMPLE>
  <SAMPLE accession="EGAN00001376845" alias="SA533642" status="PRIVATE">
    <EXT_ID accession="SAMEA3902279" type="biosample"/>
  </SAMPLE>
  <SAMPLE accession="EGAN00001376847" alias="SA520214" status="PRIVATE">
    <EXT_ID accession="SAMEA3902281" type="biosample"/>
  </SAMPLE>
  <SAMPLE accession="EGAN00001376849" alias="SA533781" status="PRIVATE">
    <EXT_ID accession="SAMEA3902283" type="biosample"/>
  </SAMPLE>
  <SAMPLE accession="EGAN00001376851" alias="SA520306" status="PRIVATE">
    <EXT_ID accession="SAMEA3902285" type="biosample"/>
  </SAMPLE>
  <SAMPLE accession="EGAN00001376853" alias="SA533714" status="PRIVATE">
    <EXT_ID accession="SAMEA3902287" type="biosample"/>
  </SAMPLE>
  <SAMPLE accession="EGAN00001376855" alias="SA558660" status="PRIVATE">
    <EXT_ID accession="SAMEA3902289" type="biosample"/>
  </SAMPLE>
  <SAMPLE accession="EGAN00001376857" alias="SA520314" status="PRIVATE">
    <EXT_ID accession="SAMEA3902291" type="biosample"/>
  </SAMPLE>
  <SAMPLE accession="EGAN00001376858" alias="SA520175" status="PRIVATE">
    <EXT_ID accession="SAMEA3902292" type="biosample"/>
  </SAMPLE>
  <SAMPLE accession="EGAN00001376860" alias="SA533651" status="PRIVATE">
    <EXT_ID accession="SAMEA3902294" type="biosample"/>
  </SAMPLE>
  <SAMPLE accession="EGAN00001376862" alias="SA533649" status="PRIVATE">
    <EXT_ID accession="SAMEA3902296" type="biosample"/>
  </SAMPLE>
  <SAMPLE accession="EGAN00001376864" alias="SA533706" status="PRIVATE">
    <EXT_ID accession="SAMEA3902298" type="biosample"/>
  </SAMPLE>
  <SAMPLE accession="EGAN00001376868" alias="SA533732" status="PRIVATE">
    <EXT_ID accession="SAMEA3902302" type="biosample"/>
  </SAMPLE>
  <SAMPLE accession="EGAN00001376870" alias="SA533720" status="PRIVATE">
    <EXT_ID accession="SAMEA3902304" type="biosample"/>
  </SAMPLE>
  <SAMPLE accession="EGAN00001376872" alias="SA558649" status="PRIVATE">
    <EXT_ID accession="SAMEA3902306" type="biosample"/>
  </SAMPLE>
  <SAMPLE accession="EGAN00001376874" alias="SA533777" status="PRIVATE">
    <EXT_ID accession="SAMEA3902308" type="biosample"/>
  </SAMPLE>
  <SAMPLE accession="EGAN00001376876" alias="SA520258" status="PRIVATE">
    <EXT_ID accession="SAMEA3902310" type="biosample"/>
  </SAMPLE>
  <SAMPLE accession="EGAN00001376878" alias="SA533646" status="PRIVATE">
    <EXT_ID accession="SAMEA3902312" type="biosample"/>
  </SAMPLE>
  <SAMPLE accession="EGAN00001376880" alias="SA533782" status="PRIVATE">
    <EXT_ID accession="SAMEA3902314" type="biosample"/>
  </SAMPLE>
  <SUBMISSION alias="1471875212_752a6531-784b-4142-8b54-bace3378a41a"/>
  <MESSAGES>
    <INFO>Submission has been committed.</INFO>
  </MESSAGES>
  <ACTIONS>MODIFY</ACTIONS>
  <ACTIONS>PROTECT</ACTIONS>
</RECEIPT>
