<?xml version="1.0" encoding="utf-8"?>
<RECEIPT receiptDate="2016-02-12T16:59:43.634Z" submissionFile="sample.LICA-FR.wgs_1455047331.submission-1455296380_121bf090-be5c-4b73-af96-173b51097731.xml" success="true">
	<SAMPLE accession="EGAN00001367365" alias="SA499627" status="PRIVATE">
		<EXT_ID accession="SAMEA3871795" type="biosample"></EXT_ID>
	</SAMPLE>
	<SAMPLE accession="EGAN00001367366" alias="SA499746" status="PRIVATE">
		<EXT_ID accession="SAMEA3871796" type="biosample"></EXT_ID>
	</SAMPLE>
	<SAMPLE accession="EGAN00001367367" alias="SA499886" status="PRIVATE">
		<EXT_ID accession="SAMEA3871797" type="biosample"></EXT_ID>
	</SAMPLE>
	<SAMPLE accession="EGAN00001367368" alias="SA499742" status="PRIVATE">
		<EXT_ID accession="SAMEA3871798" type="biosample"></EXT_ID>
	</SAMPLE>
	<SAMPLE accession="EGAN00001367369" alias="SA499715" status="PRIVATE">
		<EXT_ID accession="SAMEA3871799" type="biosample"></EXT_ID>
	</SAMPLE>
	<SAMPLE accession="EGAN00001367370" alias="SA499815" status="PRIVATE">
		<EXT_ID accession="SAMEA3871800" type="biosample"></EXT_ID>
	</SAMPLE>
	<SAMPLE accession="EGAN00001367371" alias="SA499689" status="PRIVATE">
		<EXT_ID accession="SAMEA3871801" type="biosample"></EXT_ID>
	</SAMPLE>
	<SAMPLE accession="EGAN00001367372" alias="SA499801" status="PRIVATE">
		<EXT_ID accession="SAMEA3871802" type="biosample"></EXT_ID>
	</SAMPLE>
	<SAMPLE accession="EGAN00001367373" alias="SA530169" status="PRIVATE">
		<EXT_ID accession="SAMEA3871803" type="biosample"></EXT_ID>
	</SAMPLE>
	<SAMPLE accession="EGAN00001367374" alias="SA499813" status="PRIVATE">
		<EXT_ID accession="SAMEA3871804" type="biosample"></EXT_ID>
	</SAMPLE>
	<SAMPLE accession="EGAN00001367375" alias="SA499691" status="PRIVATE">
		<EXT_ID accession="SAMEA3871805" type="biosample"></EXT_ID>
	</SAMPLE>
	<SAMPLE accession="EGAN00001367376" alias="SA499802" status="PRIVATE">
		<EXT_ID accession="SAMEA3871806" type="biosample"></EXT_ID>
	</SAMPLE>
	<SUBMISSION accession="EGA00001247528" alias="1455296380_121bf090-be5c-4b73-af96-173b51097731"></SUBMISSION>
	<MESSAGES>
		<INFO>Its ega submisison as PROTECT action is used</INFO>
		<INFO>PROTECT action for the following XML:  sample.LICA-FR.wgs_1455047331.xml</INFO>
	</MESSAGES>
	<ACTIONS>ADD</ACTIONS>
	<ACTIONS>PROTECT</ACTIONS>
</RECEIPT>